inps.py
inps-1.20.dist-info/licenses/LICENSE
inps-1.20.dist-info/WHEEL
inps-1.20.dist-info/METADATA
inps-1.20.dist-info/RECORD
