Metadata-Version: 2.4
Name: inps
Version: 1.20
Summary: Python package for statistical inference from non-probability samples
Author-email: Luis Castro Martín <luiscastro193@gmail.com>
Classifier: License :: OSI Approved :: GNU General Public License v3 or later (GPLv3+)
License-File: LICENSE
Requires-Dist: numpy
Requires-Dist: pandas
Requires-Dist: scikit-learn>=1.5
Requires-Dist: scipy
Project-URL: Home, https://github.com/luiscastro193/inps
